{
  "config": {
    "step": {
      "user": {
        "title": "Xinao Energy",
        "description": "Configure your Xinao Energy gas meter",
        "data": {
          "token": "Token",
          "device_id": "Device ID",
          "city_id": "City ID",
          "update_interval": "Update Interval (minutes)"
        }
      },
      "reconfigure": {
        "title": "Reconfigure Xinao Energy",
        "description": "Update your Xinao Energy settings",
        "data": {
          "token": "Token",
          "device_id": "Device ID",
          "city_id": "City ID",
          "update_interval": "Update Interval (minutes)"
        }
      }
    },
    "error": {
      "cannot_connect": "Failed to connect to Xinao Energy API",
      "invalid_auth": "Invalid authentication credentials",
      "unknown": "Unexpected error occurred"
    },
    "abort": {
      "already_configured": "This device is already configured",
      "reconfigure_successful": "Configuration updated successfully",
      "reconfigure_failed": "Failed to reconfigure"
    }
  },
  "options": {
    "step": {
      "init": {
        "title": "Xinao Energy Options",
        "description": "Configure update settings",
        "data": {
          "update_interval": "Update Interval (minutes)"
        }
      }
    }
  },
  "entity": {
    "sensor": {
      "balance": {
        "name": "Balance"
      },
      "gas_price": {
        "name": "Gas Price"
      },
      "today_cost": {
        "name": "Today Cost",
        "state_attributes": {
          "current_balance": {
            "name": "Current Balance"
          }
        }
      },
      "today_usage": {
        "name": "Today Usage",
        "state_attributes": {
          "gas_price": {
            "name": "Gas Price"
          }
        }
      },
      "monthly_cost": {
        "name": "Monthly Cost",
        "state_attributes": {
          "current_balance": {
            "name": "Current Balance"
          }
        }
      },
      "monthly_usage": {
        "name": "Monthly Usage",
        "state_attributes": {
          "gas_price": {
            "name": "Gas Price"
          }
        }
      },
      "last_recharge": {
        "name": "Last Recharge"
      },
      "last_recharge_time": {
        "name": "Last Recharge Time"
      }
    }
  }
}